asyncpg_engine/__init__.py
asyncpg_engine/engine.py
asyncpg_engine/pytest_plugin.py
asyncpg_engine-0.3.2.dist-info/entry_points.txt
asyncpg_engine-0.3.2.dist-info/WHEEL
asyncpg_engine-0.3.2.dist-info/LICENSE
asyncpg_engine-0.3.2.dist-info/METADATA
asyncpg_engine-0.3.2.dist-info/RECORD
