Metadata-Version: 2.1
Name: asyncpg-engine
Version: 0.3.2
Summary: Wrapper around asyncpg with a bit better experience.
Home-page: https://github.com/sivakov512/asyncpg-engine
License: MIT
Author: Nikita Sivakov
Author-email: sivakov512@icloud.com
Requires-Python: >=3.9,<4.0
Classifier: License :: OSI Approved :: MIT License
Classifier: Programming Language :: Python :: 3
Classifier: Programming Language :: Python :: 3.9
Classifier: Programming Language :: Python :: 3.10
Classifier: Programming Language :: Python :: 3.11
Requires-Dist: asyncpg (>=0.28.0,<0.29.0)
Requires-Dist: pytest (>=7.2.0,<8.0.0)
Project-URL: Repository, https://github.com/sivakov512/asyncpg-engine
